Workbook

Sheet Informações Editora Globo e SGR
A1: EMPRESA | B1: MAT | C1: NOME | D1: CARGO (SEM SENIORIDADE) | E1: LOCALIZAÇÃO | F1: CCUSTO | G1: DIRETORIA | H1: ÁREA | I1: MAT GESTOR | J1: GESTOR | K1: CCUSTO SAP
A2: 10 | B2: 110015 | C2: ANDRE FELIPE MARSON DE ANDRADE | D2: ADMINISTRADOR BANCO DE DADOS | E2: São Paulo | F2: 1142080000 | G2: TECNOLOGIA | H2: INFRAESTRUTURA TI | I2: 284913 | J2: DOUGLAS PEREIRA DA SILVA | K2: =VLOOKUP(A2,Empresas!C:E,3,0)&F2 -> 1142080000
A3: 10 | B3: 109823 | C3: RODRIGO DONIZETE PALOMBO CABRERA | D3: ADMINISTRADOR REDES | E3: São Paulo | F3: 1142080000 | G3: TECNOLOGIA | H3: INFRAESTRUTURA TI | I3: 284913 | J3: DOUGLAS PEREIRA DA SILVA | K3: =VLOOKUP(A3,Empresas!C:E,3,0)&F3 -> 1142080000
A4: 10 | B4: 284943 | C4: ANA BEATRIZ VIEIRA PODESTA | D4: ADVOGADO | E4: Rio de Janeiro | F4: 1121400000 | G4: JURÍDICO | H4: TRABALHISTA E PREVIDENCIÁRIO | I4: 108394 | J4: PRISCILA CAMPOS DE ALMEIDA FELIX | K4: =VLOOKUP(A4,Empresas!C:E,3,0)&F4 -> 1121400000
A5: 10 | B5: 283767 | C5: KAROLINE MENDONCA DE OLIVEIRA | D5: ADVOGADO | E5: Rio de Janeiro | F5: 1121400000 | G5: JURÍDICO | H5: CIVEL E CONSUMIDOR | I5: 108394 | J5: PRISCILA CAMPOS DE ALMEIDA FELIX | K5: =VLOOKUP(A5,Empresas!C:E,3,0)&F5 -> 1121400000
A6: 10 | B6: 284541 | C6: ALEANDRA RIBEIRO NASCIMENTO | D6: ADVOGADO | E6: Rio de Janeiro | F6: 1121400000 | G6: JURÍDICO | H6: CIVEL E CONSUMIDOR | I6: 108394 | J6: PRISCILA CAMPOS DE ALMEIDA FELIX | K6: =VLOOKUP(A6,Empresas!C:E,3,0)&F6 -> 1121400000
A7: 10 | B7: 285104 | C7: JULYANA MADEIRA CORREA | D7: ADVOGADO | E7: Rio de Janeiro | F7: 1121400000 | G7: JURÍDICO | H7: TRIBUTARIO, SOCIETARIO E REGULATORIO | I7: 108394 | J7: PRISCILA CAMPOS DE ALMEIDA FELIX | K7: =VLOOKUP(A7,Empresas!C:E,3,0)&F7 -> 1121400000
A8: 10 | B8: 284829 | C8: FERNANDA NEVES DE FARIAS | D8: ADVOGADO | E8: Rio de Janeiro | F8: 1121400000 | G8: JURÍDICO | H8: CIVEL E CONSUMIDOR | I8: 108394 | J8: PRISCILA CAMPOS DE ALMEIDA FELIX | K8: =VLOOKUP(A8,Empresas!C:E,3,0)&F8 -> 1121400000
A9: 10 | B9: 284022 | C9: GABRIEL FREGNI ALFIERI | D9: ADVOGADO | E9: São Paulo | F9: 1121400000 | G9: JURÍDICO | H9: TRABALHISTA E PREVIDENCIÁRIO | I9: 284949 | J9: SAMARA PESSANHA VINHOSA | K9: =VLOOKUP(A9,Empresas!C:E,3,0)&F9 -> 1121400000
A10: 10 | B10: 108908 | C10: MARY ANNE MOURA | D10: ADVOGADO | E10: Rio de Janeiro | F10: 1121400000 | G10: JURÍDICO | H10: CIVEL E CONSUMIDOR | I10: 108394 | J10: PRISCILA CAMPOS DE ALMEIDA FELIX | K10: =VLOOKUP(A10,Empresas!C:E,3,0)&F10 -> 1121400000
A11: 10 | B11: 108096 | C11: CARLOS ALBERTO BATISTA | D11: ALMOXARIFE | E11: Parque Gráfico | F11: 1141210000 | G11: SERVIÇOS IMPRESSOS | H11: LOGISTICA OPERACIONAL | I11: 108140 | J11: JOSE RICARDO DE LUCENA | K11: =VLOOKUP(A11,Empresas!C:E,3,0)&F11 -> 1141210000
A12: 10 | B12: 108408 | C12: EDSON GRIPE | D12: ALMOXARIFE | E12: Parque Gráfico | F12: 1141210000 | G12: SERVIÇOS IMPRESSOS | H12: LOGISTICA OPERACIONAL | I12: 108140 | J12: JOSE RICARDO DE LUCENA | K12: =VLOOKUP(A12,Empresas!C:E,3,0)&F12 -> 1141210000
A13: 10 | B13: 281957 | C13: EMANUEL DE LIMA FERNANDES | D13: ALMOXARIFE | E13: Parque Gráfico | F13: 1141210000 | G13: SERVIÇOS IMPRESSOS | H13: LOGISTICA OPERACIONAL | I13: 108140 | J13: JOSE RICARDO DE LUCENA | K13: =VLOOKUP(A13,Empresas!C:E,3,0)&F13 -> 1141210000
... A15: 10 | B15: 281961 | C15: WILLIAM PEREIRA DA SILVA JUNIOR | D15: ALMOXARIFE | E15: Parque Gráfico | F15: 1141210000 | G15: SERVIÇOS IMPRESSOS | H15: LOGISTICA OPERACIONAL | I15: 108140 | J15: JOSE RICARDO DE LUCENA | K15: =VLOOKUP(A15,Empresas!C:E,3,0)&F15 -> 1141210000
A16: 10 | B16: 100735 | C16: HELIO JOSE DA SILVA | D16: ANALISTA | E16: São Paulo | F16: 1122360000 | G16: LICENCIADOS BENEFICIOS | H16: LICENCIADOS BENEFICIOS | I16: - | J16: SEM GESTOR | K16: =VLOOKUP(A16,Empresas!C:E,3,0)&F16 -> 1122360000
A17: 10 | B17: 107488 | C17: PEDRO OLIVEIRA DA SILVA | D17: ANALISTA | E17: São Paulo | F17: 1431351400 | G17: AUDIÊNCIA | H17: VENDAS INDIRETAS | I17: 109048 | J17: MARIO JORGE DA SILVA PERRUT | K17: =VLOOKUP(A17,Empresas!C:E,3,0)&F17 -> 1431351400
A18: 10 | B18: 284476 | C18: KALINE DA SILVA LIMA | D18: ANALISTA | E18: Rio de Janeiro | F18: 1121110000 | G18: FINANÇAS | H18: OPERACOES FINANCEIRAS | I18: 108047 | J18: ANDREA DE ALMEIDA AMAT | K18: =VLOOKUP(A18,Empresas!C:E,3,0)&F18 -> 1121110000
A19: 10 | B19: 108861 | C19: ELLEN CRYS DE MENESES | D19: ANALISTA | E19: Rio de Janeiro | F19: 1121300000 | G19: INFRAESTRUTURA | H19: GESTÃO | I19: 108346 | J19: MAURICIO CESAR MORAES SILVA | K19: =VLOOKUP(A19,Empresas!C:E,3,0)&F19 -> 1121300000
A20: 10 | B20: 284711 | C20: JORGE LIBERATO SILVA DE JESUS | D20: ANALISTA | E20: Rio de Janeiro | F20: 1121400000 | G20: JURÍDICO | H20: ADMINISTRATIVO | I20: 108394 | J20: PRISCILA CAMPOS DE ALMEIDA FELIX | K20: =VLOOKUP(A20,Empresas!C:E,3,0)&F20 -> 1121400000
A21: 10 | B21: 283208 | C21: TEREZA CRISTINA DE CARVALHO ABDALA | D21: ANALISTA | E21: Rio de Janeiro | F21: 1121720000 | G21: FINANÇAS | H21: PLANEJAMENTO TRIBUTÁRIO | I21: 284394 | J21: MARIA DO CARMO MADUREIRA RUA | K21: =VLOOKUP(A21,Empresas!C:E,3,0)&F21 -> 1121720000
A22: 10 | B22: 107852 | C22: CESAR MEDEIROS FALCAO | D22: ANALISTA | E22: Rio de Janeiro | F22: 1122360000 | G22: LICENCIADOS BENEFICIOS | H22: LICENCIADOS BENEFICIOS | I22: - | J22: SEM GESTOR | K22: =VLOOKUP(A22,Empresas!C:E,3,0)&F22 -> 1122360000
A23: 10 | B23: 283452 | C23: LUANA DE AGUIAR GONCALVES | D23: ANALISTA | E23: Rio de Janeiro | F23: 1131361000 | G23: AUDIÊNCIA | H23: PLANEJAMENTO COMERCIAL | I23: 108708 | J23: ISIS LEMOS DE OLIVEIRA | K23: =VLOOKUP(A23,Empresas!C:E,3,0)&F23 -> 1131361000
A24: 10 | B24: 283684 | C24: DAYARA LIMA PEREIRA DE SOUZA | D24: ANALISTA | E24: Parque Gráfico | F24: 1141140000 | G24: SERVIÇOS IMPRESSOS | H24: INFRAESTRUTURA PG | I24: 108136 | J24: GEORGE FERNANDES PIMENTEL | K24: =VLOOKUP(A24,Empresas!C:E,3,0)&F24 -> 1141140000
A25: 10 | B25: 284273 | C25: SAMARA DOS SANTOS BATISTA | D25: ANALISTA | E25: Parque Gráfico | F25: 1141140000 | G25: SERVIÇOS IMPRESSOS | H25: INFRAESTRUTURA PG | I25: 108136 | J25: GEORGE FERNANDES PIMENTEL | K25: =VLOOKUP(A25,Empresas!C:E,3,0)&F25 -> 1141140000
A26: 10 | B26: 284742 | C26: FELIPE BERNARDO DA ROCHA | D26: ANALISTA | E26: Parque Gráfico | F26: 1143331107 | G26: SERVIÇOS IMPRESSOS | H26: ENTREGA DOMICILIAR | I26: 108148 | J26: ADRIANA PAULINO DA SILVA | K26: =VLOOKUP(A26,Empresas!C:E,3,0)&F26 -> 1143331107
A27: 10 | B27: 283824 | C27: ABNER LUCAS DOS SANTOS TEIXEIRA | D27: ANALISTA | E27: Rio de Janeiro | F27: 1121090000 | G27: FINANÇAS | H27: FLUXO DE CAIXA E COMISSÃO | I27: 281969 | J27: BRUNO LEONARDO COSTA SEQUEIRA | K27: =VLOOKUP(A27,Empresas!C:E,3,0)&F27 -> 1121090000
A28: 10 | B28: 284201 | C28: BARBARA DE SANTANA PINTO MOREIRA | D28: ANALISTA | E28: Rio de Janeiro | F28: 1152405000 | G28: DESENVOLVIMENTO COMERCIAL | H28: DIGITAL | I28: 108424 | J28: LEANDRO QUEIROZ FIGUEIRA | K28: =VLOOKUP(A28,Empresas!C:E,3,0)&F28 -> 1152405000
A29: 10 | B29: 284766 | C29: CLARA LIZZE PEREIRA DA SILVA | D29: ANALISTA | E29: Rio de Janeiro | F29: 1152405000 | G29: DESENVOLVIMENTO COMERCIAL | H29: DIGITAL | I29: 283248 | J29: ISADORA ANCORA DA LUZ DAMASCENO | K29: =VLOOKUP(A29,Empresas!C:E,3,0)&F29 -> 1152405000
A30: 10 | B30: 283167 | C30: THAYSA LEITE DA SILVA | D30: ANALISTA | E30: Rio de Janeiro | F30: 1152405000 | G30: DESENVOLVIMENTO COMERCIAL | H30: DIGITAL | I30: 109106 | J30: RAFAEL DE SA CENDON | K30: =VLOOKUP(A30,Empresas!C:E,3,0)&F30 -> 1152405000
A31: 10 | B31: 284667 | C31: MARIA CLARA HOMAISSI DA SILVA | D31: ANALISTA | E31: Rio de Janeiro | F31: 1152703000 | G31: DESENVOLVIMENTO COMERCIAL | H31: EVENTO | I31: 282119 | J31: CARLA DE SIMONE FERREIRA MONTENEGRO | K31: =VLOOKUP(A31,Empresas!C:E,3,0)&F31 -> 1152703000
A32: 10 | B32: 283874 | C32: BRUNA TEIXEIRA VELOSO DA FONSECA | D32: ANALISTA | E32: Rio de Janeiro | F32: 1153223000 | G32: DESENVOLVIMENTO COMERCIAL | H32: MKT PUBLICITÁRIO | I32: 108868 | J32: RAPHAEL DE BARROS RASMUSEN AMAYA | K32: =VLOOKUP(A32,Empresas!C:E,3,0)&F32 -> 1153223000
A33: 10 | B33: 285117 | C33: JULIA GRACIOLI CORREA DE SA | D33: ANALISTA | E33: Rio de Janeiro | F33: 1153223000 | G33: DESENVOLVIMENTO COMERCIAL | H33: MKT PUBLICITÁRIO | I33: 108868 | J33: RAPHAEL DE BARROS RASMUSEN AMAYA | K33: =VLOOKUP(A33,Empresas!C:E,3,0)&F33 -> 1153223000
A34: 10 | B34: 284573 | C34: BIANCA SABIONI BOECHAT ZWIRMAN | D34: ANALISTA | E34: Rio de Janeiro | F34: 1153223000 | G34: DESENVOLVIMENTO COMERCIAL | H34: MKT PUBLICITÁRIO | I34: 108868 | J34: RAPHAEL DE BARROS RASMUSEN AMAYA | K34: =VLOOKUP(A34,Empresas!C:E,3,0)&F34 -> 1153223000
... A150: 10 | B150: 108443 | C150: CATERINE JUNKO OKUMURA | D150: ANALISTA SAP ABAP | E150: Rio de Janeiro | F150: 1142600000 | G150: TECNOLOGIA | H150: SISTEMAS CORPORATIVOS | I150: 100571 | J150: RITA DE CASSIA MUTARELLI | K150: =VLOOKUP(A150,Empresas!C:E,3,0)&F150 -> 1142600000
A151: 10 | B151: 100810 | C151: MARTA NOVATO DE CARVALHO | D151: ANALISTA SERVICOS CLIENTE | E151: São Paulo | F151: 1122360000 | G151: LICENCIADOS BENEFICIOS | H151: LICENCIADOS BENEFICIOS | I151: - | J151: SEM GESTOR | K151: =VLOOKUP(A151,Empresas!C:E,3,0)&F151 -> 1122360000
A152: 10 | B152: 109791 | C152: ADENIR BARBOSA DE SOUZA | D152: ANALISTA TESTES | E152: São Paulo | F152: 1142034500 | G152: SISTEMA PRO | H152: DESENVOLVIMENTO DIGITAL - SISTEMA PRO | I152: 109677 | J152: DIOGO GUZELIAN BENTO | K152: =VLOOKUP(A152,Empresas!C:E,3,0)&F152 -> 1142034500
A153: 10 | B153: 109742 | C153: CARINA PIVA RIBEIRO | D153: ANALISTA TESTES | E153: São Paulo | F153: 1142034500 | G153: SISTEMA PRO | H153: DESENVOLVIMENTO DIGITAL - SISTEMA PRO | I153: 109677 | J153: DIOGO GUZELIAN BENTO | K153: =VLOOKUP(A153,Empresas!C:E,3,0)&F153 -> 1142034500
A154: 10 | B154: 109712 | C154: KLEBER TAKAHASHI DA SILVA | D154: ANALISTA TESTES | E154: São Paulo | F154: 1142034500 | G154: SISTEMA PRO | H154: DESENVOLVIMENTO DIGITAL - SISTEMA PRO | I154: 109677 | J154: DIOGO GUZELIAN BENTO | K154: =VLOOKUP(A154,Empresas!C:E,3,0)&F154 -> 1142034500
A155: 10 | B155: 282768 | C155: JAQUES GUIMARAES DE FREITAS | D155: ANALISTA TESTES | E155: São Paulo | F155: 1142034500 | G155: SISTEMA PRO | H155: DESENVOLVIMENTO DIGITAL - SISTEMA PRO | I155: 109677 | J155: DIOGO GUZELIAN BENTO | K155: =VLOOKUP(A155,Empresas!C:E,3,0)&F155 -> 1142034500
A156: 10 | B156: 282659 | C156: KARINA CRISTINA DA SILVA | D156: ANALISTA TESTES | E156: São Paulo | F156: 1142034500 | G156: SISTEMA PRO | H156: DESENVOLVIMENTO DIGITAL - SISTEMA PRO | I156: 109677 | J156: DIOGO GUZELIAN BENTO | K156: =VLOOKUP(A156,Empresas!C:E,3,0)&F156 -> 1142034500
A157: 10 | B157: 108331 | C157: MONICA FARIA LESSA | D157: ANL CDI | E157: Rio de Janeiro | F157: 1181100000 | G157: REDAÇÃO INTEGRADA | H157: CDI | I157: 107973 | J157: ANA CRISTINA COSTA TAVARES | K157: =VLOOKUP(A157,Empresas!C:E,3,0)&F157 -> 1181100000
A158: 10 | B158: 285033 | C158: MARIA APARECIDA CAETANO DA COSTA | D158: ANL CDI | E158: Rio de Janeiro | F158: 1181100000 | G158: REDAÇÃO INTEGRADA | H158: CDI | I158: 107973 | J158: ANA CRISTINA COSTA TAVARES | K158: =VLOOKUP(A158,Empresas!C:E,3,0)&F158 -> 1181100000
A159: 10 | B159: 108355 | C159: MARCELO ROSA CAMPOS | D159: ANL COMERCIAL AOG | E159: Rio de Janeiro | F159: 1181200000 | G159: DESENVOLVIMENTO COMERCIAL | H159: AGÊNCIA O GLOBO | I159: 108886 | J159: ALESSANDRA JASBINSCHEK | K159: =VLOOKUP(A159,Empresas!C:E,3,0)&F159 -> 1181200000
A160: 10 | B160: 282857 | C160: CARLOS MAURICIO MATHIAS LIMA | D160: ANL COMPRAS | E160: Rio de Janeiro | F160: 1144100000 | G160: FINANÇAS | H160: SUPRIMENTOS | I160: 108306 | J160: CRISTIANE TORRES COELHO MARINHO | K160: =VLOOKUP(A160,Empresas!C:E,3,0)&F160 -> 1144100000
A161: 10 | B161: 108813 | C161: MARCIO DE PAULA SANTOS | D161: ANL COMPRAS | E161: Rio de Janeiro | F161: 1144100000 | G161: FINANÇAS | H161: SUPRIMENTOS | I161: 108306 | J161: CRISTIANE TORRES COELHO MARINHO | K161: =VLOOKUP(A161,Empresas!C:E,3,0)&F161 -> 1144100000
A162: 10 | B162: 284638 | C162: JULIANA DA SILVA BARBOSA DE ALMEIDA | D162: ANL COMPRAS | E162: Rio de Janeiro | F162: 1144100000 | G162: FINANÇAS | H162: SUPRIMENTOS | I162: 108306 | J162: CRISTIANE TORRES COELHO MARINHO | K162: =VLOOKUP(A162,Empresas!C:E,3,0)&F162 -> 1144100000
A163: 10 | B163: 284512 | C163: THAIS DA SILVA CARDOSO | D163: ANL COMPRAS | E163: Rio de Janeiro | F163: 1144100000 | G163: FINANÇAS | H163: SUPRIMENTOS | I163: 281889 | J163: LUCIANE DE MATTOS FRANCISCO | K163: =VLOOKUP(A163,Empresas!C:E,3,0)&F163 -> 1144100000
... A376: 10 | B376: 284125 | C376: MARIANA KELLER SILVA | D376: ASSESSOR DE IMPRENSA GLOBO LIVROS | E376: Rio de Janeiro | F376: 5956037000 | G376: GLOBO LIVROS | H376: COMUNICAÇÃO GLOBO LIVROS | I376: 284871 | J376: TATIANE GONCALVES RAMOS | K376: =VLOOKUP(A376,Empresas!C:E,3,0)&F376 -> 5956037000
A377: 10 | B377: 107758 | C377: PAULO MALFATTI | D377: ASSESSOR DIRETORIA | E377: São Paulo | F377: 1191010000 | G377: GESTÃO DIÁRIO DE SÃO PAULO | H377: GESTÃO DIÁRIO DE SÃO PAULO | I377: - | J377: SEM GESTOR | K377: =VLOOKUP(A377,Empresas!C:E,3,0)&F377 -> 1191010000
A378: 10 | B378: 107999 | C378: MARCOS ROBERTO DA COSTA | D378: ASSIST CONTROLE FECHAMENTO | E378: Rio de Janeiro | F378: 1152623000 | G378: COMERCIAL NEGÓCIOS | H378: OPEC - RJ | I378: 283287 | J378: ALDIVO FLORO CANESSO NETO | K378: =VLOOKUP(A378,Empresas!C:E,3,0)&F378 -> 1152623000
A379: 10 | B379: 284180 | C379: CAMILA SANTANNA RANGEL DE CARVALHO | D379: ASSIST DIREITOS AUT GLOBO LIVROS | E379: Rio de Janeiro | F379: 5956007000 | G379: GLOBO LIVROS | H379: DIRETORIA DE LIVROS | I379: 104168 | J379: MAURO RIBEIRO PALERMO | K379: =VLOOKUP(A379,Empresas!C:E,3,0)&F379 -> 5956007000
A380: 10 | B380: 107737 | C380: DANIELE HENRIQUES RELVAS | D380: ASSIST EXECUTIVO | E380: Rio de Janeiro | F380: 1121400000 | G380: JURÍDICO | H380: ADMINISTRATIVO | I380: 108394 | J380: PRISCILA CAMPOS DE ALMEIDA FELIX | K380: =VLOOKUP(A380,Empresas!C:E,3,0)&F380 -> 1121400000
A381: 10 | B381: 107831 | C381: VANIA LUCIA SILVA MORAES DE VASCONCELOS | D381: ASSIST EXECUTIVO | E381: Rio de Janeiro | F381: 1122360000 | G381: LICENCIADOS BENEFICIOS | H381: LICENCIADOS BENEFICIOS | I381: - | J381: SEM GESTOR | K381: =VLOOKUP(A381,Empresas!C:E,3,0)&F381 -> 1122360000
A382: 10 | B382: 108026 | C382: NADIA REGINA DE MORAES | D382: ASSIST EXECUTIVO | E382: Rio de Janeiro | F382: 1161000000 | G382: REDAÇÃO INTEGRADA | H382: ADMINISTRATIVO | I382: 108065 | J382: ARTUR DOS SANTOS BARBOSA | K382: =VLOOKUP(A382,Empresas!C:E,3,0)&F382 -> 1161000000
A383: 10 | B383: 107892 | C383: CARMEN VERONICA VIEIRA | D383: ASSIST EXECUTIVO | E383: Rio de Janeiro | F383: 1161980000 | G383: REDAÇÃO INTEGRADA | H383: ADMINISTRATIVO | I383: 108065 | J383: ARTUR DOS SANTOS BARBOSA | K383: =VLOOKUP(A383,Empresas!C:E,3,0)&F383 -> 1161980000
A384: 10 | B384: 108664 | C384: FELIPE SILVA SOARES | D384: ASSIST EXECUTIVO | E384: Rio de Janeiro | F384: 1161980000 | G384: REDAÇÃO INTEGRADA | H384: ADMINISTRATIVO | I384: 108065 | J384: ARTUR DOS SANTOS BARBOSA | K384: =VLOOKUP(A384,Empresas!C:E,3,0)&F384 -> 1161980000
A385: 10 | B385: 107761 | C385: ANTONETE VIANA LOBO | D385: ASSIST EXECUTIVO | E385: Brasília | F385: 1173300000 | G385: REDAÇÃO INTEGRADA | H385: ADMINISTRATIVO | I385: 108065 | J385: ARTUR DOS SANTOS BARBOSA | K385: =VLOOKUP(A385,Empresas!C:E,3,0)&F385 -> 1173300000
A386: 10 | B386: 107995 | C386: RITA DE CASSIA PORTO NUNES | D386: ASSIST EXECUTIVO | E386: Rio de Janeiro | F386: 1154100000 | G386: AUDIÊNCIA | H386: DIRETORIA | I386: 109345 | J386: TIAGO JOAQUIM AFONSO | K386: =VLOOKUP(A386,Empresas!C:E,3,0)&F386 -> 1154100000
A387: 10 | B387: 108704 | C387: ALANA SOARES ALBUQUERQUE RAMIRES | D387: ASSIST EXECUTIVO | E387: Rio de Janeiro | F387: 1161000000 | G387: REDAÇÃO INTEGRADA | H387: ADMINISTRATIVO | I387: 108065 | J387: ARTUR DOS SANTOS BARBOSA | K387: =VLOOKUP(A387,Empresas!C:E,3,0)&F387 -> 1161000000
A388: 10 | B388: 284560 | C388: VINICIUS DO CARMO LOUREIRO | D388: ASSIST JURIDICO | E388: Rio de Janeiro | F388: 1121400000 | G388: JURÍDICO | H388: CONTRATOS EG | I388: 284949 | J388: SAMARA PESSANHA VINHOSA | K388: =VLOOKUP(A388,Empresas!C:E,3,0)&F388 -> 1121400000
A389: 10 | B389: 284978 | C389: ANA JULIA SILVEIRA SILVA | D389: ASSIST JURIDICO | E389: Rio de Janeiro | F389: 1121400000 | G389: JURÍDICO | H389: TRABALHISTA E PREVIDENCIÁRIO | I389: 108394 | J389: PRISCILA CAMPOS DE ALMEIDA FELIX | K389: =VLOOKUP(A389,Empresas!C:E,3,0)&F389 -> 1121400000
A390: 10 | B390: 285037 | C390: ISADORA BUNDCHEN FELISBINO LUCIANO | D390: ASSIST JURIDICO | E390: São Paulo | F390: 1121400000 | G390: JURÍDICO | H390: CONTRATOS | I390: 284949 | J390: SAMARA PESSANHA VINHOSA | K390: =VLOOKUP(A390,Empresas!C:E,3,0)&F390 -> 1121400000
A391: 10 | B391: 284158 | C391: JANAINA SILVA RODRIGUES DA COSTA | D391: ASSIST PCP | E391: Parque Gráfico | F391: 1141300000 | G391: SERVIÇOS IMPRESSOS | H391: PCP | I391: 108544 | J391: IGOR RODRIGUES MOURAO | K391: =VLOOKUP(A391,Empresas!C:E,3,0)&F391 -> 1141300000
A392: 10 | B392: 284837 | C392: YASMIN MARLI OLIVEIRA RODRIGUES | D392: ASSIST PCP | E392: Parque Gráfico | F392: 1141300000 | G392: SERVIÇOS IMPRESSOS | H392: PCP | I392: 108544 | J392: IGOR RODRIGUES MOURAO | K392: =VLOOKUP(A392,Empresas!C:E,3,0)&F392 -> 1141300000
A393: 10 | B393: 108780 | C393: RENAN ULISSES DA SILVA GUIMARAES | D393: ASSIST PROCESSOS | E393: Parque Gráfico | F393: 1141110000 | G393: SERVIÇOS IMPRESSOS | H393: PROCESSOS | I393: 108151 | J393: PAULO VITOR MOREIRA BASTOS | K393: =VLOOKUP(A393,Empresas!C:E,3,0)&F393 -> 1141110000
... A562: 10 | B562: 281675 | C562: CLARICE DA SILVA OLIVEIRA | D562: AUX ADMINISTRATIVO | E562: Rio de Janeiro | F562: 5956037000 | G562: GLOBO LIVROS | H562: COMUNICAÇÃO GLOBO LIVROS | I562: 284871 | J562: TATIANE GONCALVES RAMOS | K562: =VLOOKUP(A562,Empresas!C:E,3,0)&F562 -> 5956037000
A563: 10 | B563: 108108 | C563: LUIZ CARLOS DE OLIVEIRA FARIA | D563: AUX DISTRIBUICAO | E563: Rio de Janeiro | F563: 1122360000 | G563: LICENCIADOS BENEFICIOS | H563: LICENCIADOS BENEFICIOS | I563: - | J563: SEM GESTOR | K563: =VLOOKUP(A563,Empresas!C:E,3,0)&F563 -> 1122360000
A564: 10 | B564: 109552 | C564: ARGEMIRO DE ARAUJO MORAES | D564: AUX DISTRIBUICAO | E564: Parque Gráfico | F564: 1141211800 | G564: SERVIÇOS IMPRESSOS | H564: LOGISTICA OPERACIONAL | I564: 108575 | J564: WILLIE MENDONCA SANT ANNA | K564: =VLOOKUP(A564,Empresas!C:E,3,0)&F564 -> 1141211800
A565: 10 | B565: 283893 | C565: HANRI DOS REIS MOURA | D565: AUX DISTRIBUICAO | E565: Parque Gráfico | F565: 1141211800 | G565: SERVIÇOS IMPRESSOS | H565: LOGISTICA OPERACIONAL | I565: 108575 | J565: WILLIE MENDONCA SANT ANNA | K565: =VLOOKUP(A565,Empresas!C:E,3,0)&F565 -> 1141211800
A566: 10 | B566: 285101 | C566: EMILY GABRIEL DA SILVA | D566: AUX DISTRIBUICAO | E566: Parque Gráfico | F566: 1141211800 | G566: SERVIÇOS IMPRESSOS | H566: LOGISTICA OPERACIONAL | I566: 108575 | J566: WILLIE MENDONCA SANT ANNA | K566: =VLOOKUP(A566,Empresas!C:E,3,0)&F566 -> 1141211800
A567: 10 | B567: 284602 | C567: DALILA CONCEICAO DA SILVA | D567: AUX DISTRIBUICAO | E567: Parque Gráfico | F567: 1141211800 | G567: SERVIÇOS IMPRESSOS | H567: LOGISTICA OPERACIONAL | I567: 108575 | J567: WILLIE MENDONCA SANT ANNA | K567: =VLOOKUP(A567,Empresas!C:E,3,0)&F567 -> 1141211800
A568: 10 | B568: 284598 | C568: GABRIEL WALKER DE MATOS RIBEIRO | D568: AUX DISTRIBUICAO | E568: Parque Gráfico | F568: 1141211800 | G568: SERVIÇOS IMPRESSOS | H568: LOGISTICA OPERACIONAL | I568: 108575 | J568: WILLIE MENDONCA SANT ANNA | K568: =VLOOKUP(A568,Empresas!C:E,3,0)&F568 -> 1141211800
A569: 10 | B569: 284230 | C569: NILBER FERREIRA PINTO | D569: AUX DISTRIBUICAO | E569: Parque Gráfico | F569: 1141211800 | G569: SERVIÇOS IMPRESSOS | H569: LOGISTICA OPERACIONAL | I569: 108575 | J569: WILLIE MENDONCA SANT ANNA | K569: =VLOOKUP(A569,Empresas!C:E,3,0)&F569 -> 1141211800
A570: 10 | B570: 108255 | C570: ALCINO CANINDE DA SILVA | D570: AUX DISTRIBUICAO | E570: Parque Gráfico | F570: 1143251000 | G570: SERVIÇOS IMPRESSOS | H570: LOGISTICA OPERACIONAL | I570: 108070 | J570: NOVAES TEIXEIRA DUTRA | K570: =VLOOKUP(A570,Empresas!C:E,3,0)&F570 -> 1143251000
A571: 10 | B571: 107963 | C571: ALDIR LOPES DE FARIA | D571: AUX DISTRIBUICAO | E571: Parque Gráfico | F571: 1143251000 | G571: SERVIÇOS IMPRESSOS | H571: LOGISTICA OPERACIONAL | I571: 108070 | J571: NOVAES TEIXEIRA DUTRA | K571: =VLOOKUP(A571,Empresas!C:E,3,0)&F571 -> 1143251000
A572: 10 | B572: 285102 | C572: PAULO RICARDO PEQUENO PONTEIRO | D572: AUX DISTRIBUICAO | E572: Parque Gráfico | F572: 1143251000 | G572: SERVIÇOS IMPRESSOS | H572: LOGISTICA OPERACIONAL | I572: 108070 | J572: NOVAES TEIXEIRA DUTRA | K572: =VLOOKUP(A572,Empresas!C:E,3,0)&F572 -> 1143251000
A573: 10 | B573: 108125 | C573: CARLOS ROBERTO RANGEL DE ALMEIDA | D573: AUX DISTRIBUICAO | E573: Parque Gráfico | F573: 1143251000 | G573: SERVIÇOS IMPRESSOS | H573: LOGISTICA OPERACIONAL | I573: 108239 | J573: PAULO ROBERTO ALAMBERT | K573: =VLOOKUP(A573,Empresas!C:E,3,0)&F573 -> 1143251000
A574: 10 | B574: 284851 | C574: BRYAN GOMES DA COSTA | D574: AUX DISTRIBUICAO | E574: Parque Gráfico | F574: 1143251000 | G574: SERVIÇOS IMPRESSOS | H574: LOGISTICA OPERACIONAL | I574: 108070 | J574: NOVAES TEIXEIRA DUTRA | K574: =VLOOKUP(A574,Empresas!C:E,3,0)&F574 -> 1143251000
A575: 10 | B575: 284852 | C575: RENARD DA SILVA RANGEL | D575: AUX DISTRIBUICAO | E575: Parque Gráfico | F575: 1143251000 | G575: SERVIÇOS IMPRESSOS | H575: LOGISTICA OPERACIONAL | I575: 108070 | J575: NOVAES TEIXEIRA DUTRA | K575: =VLOOKUP(A575,Empresas!C:E,3,0)&F575 -> 1143251000
... A602: 10 | B602: 284080 | C602: PATRICK SILVA DE SOUZA | D602: AUX IMPRESSAO | E602: Parque Gráfico | F602: 1141130000 | G602: SERVIÇOS IMPRESSOS | H602: PRÉ IMPRESSÃO | I602: 108139 | J602: ALEXANDRE SIMON | K602: =VLOOKUP(A602,Empresas!C:E,3,0)&F602 -> 1141130000
A603: 10 | B603: 107792 | C603: VAGNER IGNACIO ALBUQUERQUE | D603: AUX IMPRESSAO | E603: São Paulo | F603: 1191010000 | G603: GESTÃO DIÁRIO DE SÃO PAULO | H603: GESTÃO DIÁRIO DE SÃO PAULO | I603: - | J603: SEM GESTOR | K603: =VLOOKUP(A603,Empresas!C:E,3,0)&F603 -> 1191010000
A604: 10 | B604: 108713 | C604: ADOLFO RIBEIRO DE OLIVEIRA MACIEL | D604: AUX IMPRESSAO | E604: Parque Gráfico | F604: 1141110000 | G604: SERVIÇOS IMPRESSOS | H604: IMPRESSÃO | I604: 108151 | J604: PAULO VITOR MOREIRA BASTOS | K604: =VLOOKUP(A604,Empresas!C:E,3,0)&F604 -> 1141110000
A605: 10 | B605: 108873 | C605: ANDRE LUIS DA SILVA PIEDADE | D605: AUX IMPRESSAO | E605: Parque Gráfico | F605: 1141110000 | G605: SERVIÇOS IMPRESSOS | H605: IMPRESSÃO | I605: 108050 | J605: WELLINGTON TINOCO LANDIM | K605: =VLOOKUP(A605,Empresas!C:E,3,0)&F605 -> 1141110000
A606: 10 | B606: 109532 | C606: CLOVIS BATISTA SOARES | D606: AUX IMPRESSAO | E606: Parque Gráfico | F606: 1141110000 | G606: SERVIÇOS IMPRESSOS | H606: IMPRESSÃO | I606: 108050 | J606: WELLINGTON TINOCO LANDIM | K606: =VLOOKUP(A606,Empresas!C:E,3,0)&F606 -> 1141110000
A607: 10 | B607: 108800 | C607: RAPHAEL MARUCHE RICCIO DE CARVALHO | D607: AUX IMPRESSAO | E607: Parque Gráfico | F607: 1141110000 | G607: SERVIÇOS IMPRESSOS | H607: IMPRESSÃO | I607: 108188 | J607: ANTONIO FERREIRA DA SILVA | K607: =VLOOKUP(A607,Empresas!C:E,3,0)&F607 -> 1141110000
A608: 10 | B608: 108059 | C608: MARIO JOSE DA FONSECA FILHO | D608: AUX IMPRESSAO | E608: Rio de Janeiro | F608: 1122360000 | G608: LICENCIADOS BENEFICIOS | H608: LICENCIADOS BENEFICIOS | I608: - | J608: SEM GESTOR | K608: =VLOOKUP(A608,Empresas!C:E,3,0)&F608 -> 1122360000
A609: 10 | B609: 108110 | C609: FRANCISMAR PEREIRA DE SOUZA | D609: AUX IMPRESSAO | E609: Parque Gráfico | F609: 1141110000 | G609: SERVIÇOS IMPRESSOS | H609: IMPRESSÃO | I609: 108050 | J609: WELLINGTON TINOCO LANDIM | K609: =VLOOKUP(A609,Empresas!C:E,3,0)&F609 -> 1141110000
A610: 10 | B610: 107984 | C610: RONALDO ALVES DA SILVA | D610: AUX IMPRESSAO | E610: Parque Gráfico | F610: 1141110000 | G610: SERVIÇOS IMPRESSOS | H610: IMPRESSÃO | I610: 108188 | J610: ANTONIO FERREIRA DA SILVA | K610: =VLOOKUP(A610,Empresas!C:E,3,0)&F610 -> 1141110000
A611: 10 | B611: 108285 | C611: MATHEUS MARTINS DA CONCEICAO | D611: AUX IMPRESSAO | E611: Parque Gráfico | F611: 1141110000 | G611: SERVIÇOS IMPRESSOS | H611: IMPRESSÃO | I611: 108050 | J611: WELLINGTON TINOCO LANDIM | K611: =VLOOKUP(A611,Empresas!C:E,3,0)&F611 -> 1141110000
A612: 10 | B612: 284912 | C612: ESTEFANIA BERRINI DA FONSECA | D612: AUXILIAR ADMINISTRATIVO | E612: Rio de Janeiro | F612: 1122250000 | G612: LIVRE ACESSO | H612: CDI | I612: 107973 | J612: ANA CRISTINA COSTA TAVARES | K612: =VLOOKUP(A612,Empresas!C:E,3,0)&F612 -> 1122250000
A613: 10 | B613: 284513 | C613: CLIZIA OLIVEIRA SOUZA | D613: AUXILIAR ADMINISTRATIVO | E613: Rio de Janeiro | F613: 1122250000 | G613: LIVRE ACESSO | H613: ADMINISTRATIVO | I613: 108516 | J613: ANA CAROLINA DE SOUZA PEREIRA CORDOVA | K613: =VLOOKUP(A613,Empresas!C:E,3,0)&F613 -> 1122250000
A614: 10 | B614: 284672 | C614: INGRIT DA SILVA LIMA | D614: AUXILIAR ADMINISTRATIVO | E614: Rio de Janeiro | F614: 1122250000 | G614: LIVRE ACESSO | H614: PLANEJAMENTO TRIBUTÁRIO | I614: 284394 | J614: MARIA DO CARMO MADUREIRA RUA | K614: =VLOOKUP(A614,Empresas!C:E,3,0)&F614 -> 1122250000
A615: 10 | B615: 283846 | C615: BEATRIZ MARINHO FERREIRA | D615: AUXILIAR ADMINISTRATIVO | E615: Parque Gráfico | F615: 1122250000 | G615: LIVRE ACESSO | H615: LOGISTICA OPERACIONAL | I615: 108239 | J615: PAULO ROBERTO ALAMBERT | K615: =VLOOKUP(A615,Empresas!C:E,3,0)&F615 -> 1122250000
A616: 10 | B616: 282524 | C616: CAMILA DE JESUS CALVI | D616: AUXILIAR ADMINISTRATIVO | E616: Rio de Janeiro | F616: 1122250000 | G616: LIVRE ACESSO | H616: PLANEJAMENTO TRIBUTÁRIO | I616: 284394 | J616: MARIA DO CARMO MADUREIRA RUA | K616: =VLOOKUP(A616,Empresas!C:E,3,0)&F616 -> 1122250000
A617: 10 | B617: 284650 | C617: DANIEL POLYDORO GONZALEZ FERNANDEZ | D617: AUXILIAR ADMINISTRATIVO | E617: Rio de Janeiro | F617: 1122250000 | G617: LIVRE ACESSO | H617: ADMINISTRATIVO | I617: 108065 | J617: ARTUR DOS SANTOS BARBOSA | K617: =VLOOKUP(A617,Empresas!C:E,3,0)&F617 -> 1122250000
A618: 10 | B618: 284740 | C618: LAIS BARBOSA DOS SANTOS | D618: AUXILIAR ADMINISTRATIVO | E618: Rio de Janeiro | F618: 1122250000 | G618: LIVRE ACESSO | H618: ADMINISTRATIVO | I618: 108516 | J618: ANA CAROLINA DE SOUZA PEREIRA CORDOVA | K618: =VLOOKUP(A618,Empresas!C:E,3,0)&F618 -> 1122250000
A619: 10 | B619: 284253 | C619: ELISAMA SOARES ILDEFONSO | D619: AUXILIAR ADMINISTRATIVO | E619: Rio de Janeiro | F619: 1122250000 | G619: LIVRE ACESSO | H619: AGÊNCIA O GLOBO | I619: 108886 | J619: ALESSANDRA JASBINSCHEK | K619: =VLOOKUP(A619,Empresas!C:E,3,0)&F619 -> 1122250000
A620: 10 | B620: 284578 | C620: ALINE DE AZEVEDO FERNANDES | D620: AUXILIAR ADMINISTRATIVO | E620: Rio de Janeiro | F620: 1122250000 | G620: LIVRE ACESSO | H620: ADMINISTRATIVO | I620: 108516 | J620: ANA CAROLINA DE SOUZA PEREIRA CORDOVA | K620: =VLOOKUP(A620,Empresas!C:E,3,0)&F620 -> 1122250000
... A642: 10 | B642: 283239 | C642: THIAGO BRONZATTO | D642: CH REDACAO BRASILIA | E642: Brasília | F642: 1173300000 | G642: REDAÇÃO INTEGRADA | H642: SUCURSAL BRASÍLIA | I642: 108965 | J642: ALAN ONOFRE GRIPP | K642: =VLOOKUP(A642,Empresas!C:E,3,0)&F642 -> 1173300000
A643: 10 | B643: 107756 | C643: BENTO DA SILVA | D643: CH TRAFEGO | E643: São Paulo | F643: 1191010000 | G643: GESTÃO DIÁRIO DE SÃO PAULO | H643: GESTÃO DIÁRIO DE SÃO PAULO | I643: - | J643: SEM GESTOR | K643: =VLOOKUP(A643,Empresas!C:E,3,0)&F643 -> 1191010000
...

Sheet Empresas
B2: EMPRESA | C2: CÓDIGO | D2: NOME | E2: LETRA
B3: SGR | C3: 571 | D3: RÁDIO GLOBO | E3: G
B4: SGR | C4: 572 | D4: BH | E4: H
B5: SGR | C5: 573 | D5: CAETÉ | E5: T
B6: SGR | C6: 574 | D6: EXCELSIOR | E6: X
B7: SGR | C7: 575 | D7: ELDORADO | E7: E
B8: EG | C8: 10 | D8: EDITORA GLOBO
